sphinx_term/__init__.py
sphinx_term/cssterm.py
sphinx_term/termynal.py
sphinx_term/_static/README.md
sphinx_term/_static/cssterm/css/cssterm.css
sphinx_term/_static/cssterm/scripts/cssterm.js
sphinx_term/_static/termynal/termynal.css
sphinx_term/_static/termynal/termynal.js
sphinx_term-0.1.dist-info/LICENCE
sphinx_term-0.1.dist-info/METADATA
sphinx_term-0.1.dist-info/WHEEL
sphinx_term-0.1.dist-info/top_level.txt
sphinx_term-0.1.dist-info/RECORD
