Metadata-Version: 2.1
Name: sphinx-term
Version: 0.1
Summary: A collection of Sphinx (and Jupyter Book) extensions for authoring vivacious terminal transcripts.
Home-page: https://github.com/So-Cool/sphinx-term
Maintainer: Kacper Sokol
Maintainer-email: ks1591@my.bristol.ac.uk
License: new BSD
Download-URL: https://pypi.org/project/sphinx-term/#files
Platform: UNKNOWN
Requires-Python: ~=3.5
